aie_feast/__init__.py
aie_feast/featurestore.py
aie_feast/service.py
aie_feast/views.py
aie_feast/definitions/__init__.py
aie_feast/definitions/constants.py
aie_feast/definitions/dtypes.py
aie_feast/definitions/entities.py
aie_feast/definitions/features.py
aie_feast/definitions/period.py
f2ai-0.0.4.dist-info/METADATA
f2ai-0.0.4.dist-info/WHEEL
f2ai-0.0.4.dist-info/top_level.txt
f2ai-0.0.4.dist-info/RECORD
