Metadata-Version: 2.1
Name: f2ai
Version: 0.0.4
Home-page: https://github.com/ai-excelsior/F2AI
Author: 
License: MIT
Requires-Dist: pandas (==1.4.0)
Requires-Dist: pyyaml (==6.0)
Requires-Dist: python-dateutil (==2.8.2)
Requires-Dist: psycopg2-binary (==2.9.5)
Requires-Dist: torch (==1.11.0)
Requires-Dist: SQLAlchemy (==1.4.31)
Requires-Dist: pypika (==0.48.9)
Requires-Dist: dill (==0.3.6)
Requires-Dist: pydantic (==1.10.2)
Requires-Dist: docker (==6.0.0)
Requires-Dist: oss2 (==2.16.0)
Requires-Dist: Jinja2
